munin_plot-1.10.dist-info/licenses/COPYING
muninplot/__init__.py
muninplot/__main__.py
muninplot/data.py
muninplot/wsgi.py
muninplot/static/apple-touch-icon.png
muninplot/static/favicon-16x16.png
muninplot/static/favicon-32x32.png
muninplot/static/favicon-64x64.png
muninplot/static/favicon.ico
muninplot/static/index.html
muninplot/static/logo.png
muninplot/static/munin-plot.ec56fe100c69a737411c.js
muninplot/static/munin-plot.ec56fe100c69a737411c.js.LICENSE.txt
muninplot/static/munin-plot.ff3f5d1211e2b68d1fa8.css
muninplot/static/munin-plot.zip
munin_plot-1.10.dist-info/METADATA
munin_plot-1.10.dist-info/WHEEL
munin_plot-1.10.dist-info/top_level.txt
munin_plot-1.10.dist-info/RECORD
