Metadata-Version: 2.4
Name: munin-plot
Version: 1.10
Summary: Alternative web front-end for Munin
Home-page: https://arthurdejong.org/munin-plot/
Author: Arthur de Jong
Author-email: arthur@arthurdejong.org
License: MIT
Classifier: Development Status :: 3 - Alpha
Classifier: Environment :: Web Environment
Classifier: Intended Audience :: Developers
Classifier: Intended Audience :: System Administrators
Classifier: License :: OSI Approved :: MIT License
Classifier: Operating System :: OS Independent
Classifier: Programming Language :: Python
Classifier: Programming Language :: Python :: 3
Classifier: Topic :: Internet :: WWW/HTTP :: Dynamic Content
Classifier: Topic :: Internet :: WWW/HTTP :: WSGI :: Application
Classifier: Topic :: System :: Monitoring
Classifier: Topic :: System :: Networking :: Monitoring
Requires-Python: >=3
License-File: COPYING
Dynamic: license-file
